{
	"tableId": "ACSDT1Y2024.B01002C",
	"title": "Median Age by Sex (American Indian and Alaska Native Alone)",
	"survey": "ACS 1-Year Estimates Detailed Tables",
	"universe": "People who are American Indian and Alaska Native alone",
	"year": "2024",
	"vintage": "2024",
	"url": "https://data.census.gov/table?tid=ACSDT1Y2024.B01002C",
	"geography": "Geography",
	"variables": {
		"measures": [
			{
				"id": "B01002C_001E",
				"label": "Estimate!!Median age --!!Total:"
			},
			{
				"id": "B01002C_001M",
				"label": "Margin of Error!!Median age --!!Total:"
			},
			{
				"id": "B01002C_002E",
				"label": "Estimate!!Median age --!!Male"
			},
			{
				"id": "B01002C_002M",
				"label": "Margin of Error!!Median age --!!Male"
			},
			{
				"id": "B01002C_003E",
				"label": "Estimate!!Median age --!!Female"
			},
			{
				"id": "B01002C_003M",
				"label": "Margin of Error!!Median age --!!Female"
			}
		],
		"dimensions": [
			{
				"id": "GEO",
				"label": "Geography",
				"dimensionType": "GEOGRAPHY"
			},
			{
				"id": "ESTIMATE",
				"dimensionType": "MEASURE"
			},
			{
				"id": "SUBJECT",
				"dimensionType": "MEASURE"
			}
		]
	},
	"data": [
		[
			"B01002C_001M",
			"B01002C_002M",
			"B01002C_003M",
			"B01002C_001EA",
			"B01002C_002EA",
			"B01002C_003EA",
			"NAME",
			"B01002C_001MA",
			"GEO_ID",
			"B01002C_002MA",
			"B01002C_003MA",
			"B01002C_001E",
			"B01002C_002E",
			"B01002C_003E"
		],
		[
			"0.3",
			"0.4",
			"0.4",
			null,
			null,
			null,
			"United States",
			null,
			"0100000US",
			null,
			null,
			"34.2",
			"33.9",
			"34.6"
		]
	],
	"scrapedTimestamp": "2025-12-09T20:59:27.487Z"
}